fastshap/__init__.py
fastshap/_nbdev.py
fastshap/core.py
fastshap/interp.py
fastshapv1-0.0.10.dist-info/DESCRIPTION.rst
fastshapv1-0.0.10.dist-info/METADATA
fastshapv1-0.0.10.dist-info/RECORD
fastshapv1-0.0.10.dist-info/WHEEL
fastshapv1-0.0.10.dist-info/entry_points.txt
fastshapv1-0.0.10.dist-info/metadata.json
fastshapv1-0.0.10.dist-info/top_level.txt
