Metadata-Version: 2.0
Name: fastshapv1
Version: 0.0.10
Summary: A shap wrapper for fastai
Home-page: https://github.com/muellerzr/fastshapv1
Author: Zach Mueller
Author-email: muellerzr@gmail.com
License: Apache Software License 2.0
Keywords: f,a,s,t,a,i,2, ,s,h,a,p
Platform: UNKNOWN
Classifier: Development Status :: 3 - Alpha
Classifier: Intended Audience :: Developers
Classifier: License :: OSI Approved :: Apache Software License
Classifier: Natural Language :: English
Classifier: Programming Language :: Python :: 3.6
Classifier: Programming Language :: Python :: 3.7
Classifier: Programming Language :: Python :: 3.8
Requires-Python: >=3.6
Requires-Dist: fastai
Requires-Dist: fastcore
Requires-Dist: shap
